repo_tool/__init__.py
repo_tool/common.py
repo_tool/lib_get.py
repo_tool/lib_repo.py
lib_repo_tool-2.0.8.dist-info/METADATA
lib_repo_tool-2.0.8.dist-info/WHEEL
lib_repo_tool-2.0.8.dist-info/entry_points.txt
lib_repo_tool-2.0.8.dist-info/top_level.txt
lib_repo_tool-2.0.8.dist-info/RECORD
