Metadata-Version: 2.1
Name: lib-repo-tool
Version: 2.0.8
Summary: Put depended libs to oss file bucket
Home-page: UNKNOWN
Author: Andy Zhuang
Author-email: xiaolong.zhuang@gmail.com
License: UNKNOWN
Platform: UNKNOWN
Requires-Dist: oss2 (==2.14.0)
Requires-Dist: dacite (==1.6.0)
Requires-Dist: tabulate
